{"users":[{"profile_background_color":"8B542B","protected":false,"profile_image_url_https":"https:\/\/si0.twimg.com\/profile_images\/1367617076\/image_normal.jpg","profile_background_image_url":"http:\/\/a1.twimg.com\/profile_background_images\/18024803\/coffeebean.jpg","name":"Roy Cornelissen","contributors_enabled":false,"statuses_count":10977,"default_profile_image":false,"utc_offset":3600,"profile_text_color":"333333","profile_image_url":"http:\/\/a2.twimg.com\/profile_images\/1367617076\/image_normal.jpg","following":false,"friends_count":702,"profile_sidebar_fill_color":"EADEAA","description":"Software architect. Cooking fanatic. Hobby photographer. iPhone fanboy. Microsoft lover. Husband. Dad. \uf8ff","location":"Doetinchem, Netherlands","id_str":"26448042","is_translator":false,"verified":false,"profile_background_tile":true,"followers_count":470,"screen_name":"roycornelissen","status":{"place":null,"geo":null,"in_reply_to_user_id":null,"text":"Altijd erg leuk om bij Oil & Vinegar rond te struinen, maar het is zeker zo leuk om dat allemaal zelf te maken... En vaak nog lekkerder...","retweet_count":0,"id_str":"89298268902793216","favorited":false,"in_reply_to_status_id_str":null,"coordinates":null,"truncated":false,"in_reply_to_screen_name":null,"id":89298268902793216,"in_reply_to_user_id_str":null,"source":"\u003Ca href=\"http:\/\/twitter.com\/#!\/download\/iphone\" rel=\"nofollow\"\u003ETwitter for iPhone\u003C\/a\u003E","created_at":"Fri Jul 08 11:42:21 +0000 2011","contributors":null,"retweeted":false,"in_reply_to_status_id":null},"follow_request_sent":false,"url":"http:\/\/about.me\/roycornelissen","profile_link_color":"9D582E","id":26448042,"notifications":false,"created_at":"Wed Mar 25 06:49:06 +0000 2009","profile_sidebar_border_color":"D9B17E","time_zone":"Amsterdam","default_profile":false,"show_all_inline_media":false,"listed_count":20,"lang":"en","geo_enabled":true,"profile_use_background_image":true,"profile_background_image_url_https":"https:\/\/si0.twimg.com\/profile_background_images\/18024803\/coffeebean.jpg","favourites_count":33},{"is_translator":false,"profile_background_image_url_https":"https:\/\/si0.twimg.com\/images\/themes\/theme1\/bg.png","profile_background_color":"C0DEED","protected":false,"follow_request_sent":null,"profile_background_image_url":"http:\/\/a0.twimg.com\/images\/themes\/theme1\/bg.png","friends_count":90,"name":"Victor van Doorn","statuses_count":140,"default_profile":true,"utc_offset":null,"profile_text_color":"333333","profile_image_url":"http:\/\/a1.twimg.com\/profile_images\/1215137084\/Victor_crop_normal.jpg","following":null,"profile_sidebar_fill_color":"DDEEF6","description":"Social not working expert.","location":"Amsterdam","id_str":"157643177","listed_count":5,"verified":false,"profile_background_tile":false,"followers_count":100,"screen_name":"VictorvanDoorn","status":{"place":null,"geo":null,"in_reply_to_user_id":20639553,"text":"@frantastique u got it","retweet_count":0,"id_str":"88229767379292160","favorited":false,"in_reply_to_status_id_str":"88228451420614656","coordinates":null,"truncated":false,"in_reply_to_screen_name":"frantastique","id":88229767379292160,"in_reply_to_user_id_str":"20639553","source":"web","created_at":"Tue Jul 05 12:56:30 +0000 2011","contributors":null,"retweeted":false,"in_reply_to_status_id":88228451420614656},"geo_enabled":true,"url":"http:\/\/www.lightstorm.nl","profile_link_color":"0084B4","profile_image_url_https":"https:\/\/si0.twimg.com\/profile_images\/1215137084\/Victor_crop_normal.jpg","id":157643177,"show_all_inline_media":false,"notifications":null,"created_at":"Sun Jun 20 12:25:09 +0000 2010","profile_sidebar_border_color":"C0DEED","default_profile_image":false,"contributors_enabled":false,"time_zone":null,"lang":"en","profile_use_background_image":true,"favourites_count":0},{"is_translator":false,"profile_background_color":"1A1B1F","protected":false,"follow_request_sent":false,"profile_background_image_url":"http:\/\/a1.twimg.com\/images\/themes\/theme9\/bg.gif","name":"Dynaloo Media","default_profile":false,"utc_offset":3600,"profile_text_color":"666666","profile_image_url":"http:\/\/a0.twimg.com\/profile_images\/1304720952\/logo_dynaloo_media_001_normal.png","following":false,"profile_sidebar_fill_color":"252429","description":"#iOS App development | Web applications | Founder of the Queensday iPhone app http:\/\/itun.es\/i6d4Hj","location":"Barneveld, The Netherlands","id_str":"278727758","listed_count":2,"verified":false,"profile_background_tile":false,"profile_background_image_url_https":"https:\/\/si0.twimg.com\/images\/themes\/theme9\/bg.gif","followers_count":79,"screen_name":"dynaloomedia","status":{"retweeted_status":{"place":null,"geo":null,"in_reply_to_user_id":null,"text":"Apple heeft miljard dollar verdiend aan iOS-ontwikkelaars - tweakers.net http:\/\/bit.ly\/qYnA8X #mobiel #mdbtw","retweet_count":1,"id_str":"89318635688034305","favorited":false,"in_reply_to_status_id_str":null,"coordinates":null,"truncated":false,"in_reply_to_screen_name":null,"id":89318635688034305,"in_reply_to_user_id_str":null,"source":"\u003Ca href=\"http:\/\/twitterfeed.com\" rel=\"nofollow\"\u003Etwitterfeed\u003C\/a\u003E","created_at":"Fri Jul 08 13:03:16 +0000 2011","contributors":null,"retweeted":false,"in_reply_to_status_id":null},"place":null,"geo":null,"in_reply_to_user_id":null,"text":"RT @MobileNL: Apple heeft miljard dollar verdiend aan iOS-ontwikkelaars - tweakers.net http:\/\/bit.ly\/qYnA8X #mobiel #mdbtw","retweet_count":1,"id_str":"89349149161566208","favorited":false,"in_reply_to_status_id_str":null,"coordinates":null,"truncated":false,"in_reply_to_screen_name":null,"id":89349149161566208,"in_reply_to_user_id_str":null,"source":"web","created_at":"Fri Jul 08 15:04:31 +0000 2011","contributors":null,"retweeted":false,"in_reply_to_status_id":null},"url":"http:\/\/www.dynaloomedia.com\/","profile_image_url_https":"https:\/\/si0.twimg.com\/profile_images\/1304720952\/logo_dynaloo_media_001_normal.png","show_all_inline_media":false,"geo_enabled":false,"profile_link_color":"2FC2EF","id":278727758,"contributors_enabled":false,"notifications":false,"created_at":"Thu Apr 07 21:12:50 +0000 2011","profile_sidebar_border_color":"181A1E","default_profile_image":false,"time_zone":"Amsterdam","lang":"en","statuses_count":89,"profile_use_background_image":true,"favourites_count":0,"friends_count":212},{"is_translator":false,"profile_background_image_url_https":"https:\/\/si0.twimg.com\/images\/themes\/theme1\/bg.png","profile_background_color":"199ee5","protected":false,"follow_request_sent":null,"profile_background_image_url":"http:\/\/a0.twimg.com\/images\/themes\/theme1\/bg.png","friends_count":136,"name":"IceMobile","statuses_count":59,"default_profile":false,"utc_offset":null,"profile_text_color":"333333","profile_image_url":"http:\/\/a3.twimg.com\/profile_images\/1178269323\/IceMobile_logo-02_normal.png","following":null,"profile_sidebar_fill_color":"ffffff","description":"IceMobile is a full service mobile agency ","location":"Amsterdam, the Netherlands","id_str":"126599614","listed_count":10,"verified":false,"profile_background_tile":false,"followers_count":140,"screen_name":"icemobile","status":{"place":null,"geo":null,"in_reply_to_user_id":null,"text":"IceMobile's latest project... http:\/\/fb.me\/ZN0oYEgZ","retweet_count":1,"id_str":"89324131568459776","favorited":false,"in_reply_to_status_id_str":null,"coordinates":null,"truncated":false,"in_reply_to_screen_name":null,"id":89324131568459776,"in_reply_to_user_id_str":null,"source":"\u003Ca href=\"http:\/\/www.facebook.com\/twitter\" rel=\"nofollow\"\u003EFacebook\u003C\/a\u003E","created_at":"Fri Jul 08 13:25:07 +0000 2011","contributors":null,"retweeted":false,"in_reply_to_status_id":null},"geo_enabled":false,"url":"http:\/\/www.icemobile.com","profile_link_color":"0084B4","profile_image_url_https":"https:\/\/si0.twimg.com\/profile_images\/1178269323\/IceMobile_logo-02_normal.png","id":126599614,"show_all_inline_media":false,"notifications":null,"created_at":"Fri Mar 26 11:28:45 +0000 2010","profile_sidebar_border_color":"C0DEED","default_profile_image":false,"contributors_enabled":false,"time_zone":null,"lang":"en","profile_use_background_image":false,"favourites_count":0},{"listed_count":22,"time_zone":"Amsterdam","screen_name":"marcschoneveld","statuses_count":1247,"profile_use_background_image":true,"favourites_count":2,"url":null,"description":"Deeltijd medewerker voor de gemeente Amsterdam, tweets op persoonlijke titel. Fan van #oif020, #openinnovatie en #opendata. Politieke kleur: autonoom","status":{"contributors":null,"retweeted":false,"in_reply_to_status_id":null,"text":"A 3D printer that uses chocolate has been developed, it prints layers of chocolate instead of ink or plastic http:\/\/bbc.in\/pfucmK #lekker","created_at":"Wed Jul 06 07:13:23 +0000 2011","source":"\u003Ca href=\"http:\/\/seesmic.com\/\" rel=\"nofollow\"\u003ESeesmic\u003C\/a\u003E","geo":null,"in_reply_to_user_id":null,"place":null,"retweet_count":0,"id_str":"88505808534503424","favorited":false,"in_reply_to_status_id_str":null,"coordinates":null,"truncated":false,"in_reply_to_screen_name":null,"id":88505808534503424,"in_reply_to_user_id_str":null},"profile_background_image_url_https":"https:\/\/si0.twimg.com\/profile_background_images\/201820351\/CRI_106848.jpg","profile_background_color":"ffffff","profile_background_image_url":"http:\/\/a3.twimg.com\/profile_background_images\/201820351\/CRI_106848.jpg","created_at":"Wed Aug 12 19:19:56 +0000 2009","profile_image_url_https":"https:\/\/si0.twimg.com\/profile_images\/554904747\/marcschoneveld2_normal.jpg","default_profile_image":false,"contributors_enabled":false,"lang":"en","profile_text_color":"4d4c4c","is_translator":false,"profile_sidebar_fill_color":"d6d6d6","id_str":"65130909","follow_request_sent":false,"verified":false,"profile_background_tile":true,"friends_count":332,"followers_count":332,"protected":false,"name":"marc schoneveld","default_profile":false,"show_all_inline_media":false,"geo_enabled":true,"profile_link_color":"00ccff","profile_image_url":"http:\/\/a3.twimg.com\/profile_images\/554904747\/marcschoneveld2_normal.jpg","id":65130909,"following":false,"notifications":false,"utc_offset":3600,"profile_sidebar_border_color":"ebebeb","location":"Amsterdam"},{"time_zone":"Amsterdam","screen_name":"florisva","listed_count":4,"profile_use_background_image":true,"favourites_count":0,"url":"http:\/\/solidventures.nl","description":"Seed and early stage investor in IT companies","status":{"contributors":null,"retweeted":false,"in_reply_to_status_id":null,"text":"Heading to NDSM for the #Appsterdam brunch","created_at":"Sun Jun 26 10:39:46 +0000 2011","source":"web","geo":null,"in_reply_to_user_id":null,"place":null,"retweet_count":0,"id_str":"84933867718443008","favorited":false,"in_reply_to_status_id_str":null,"coordinates":null,"truncated":false,"in_reply_to_screen_name":null,"id":84933867718443008,"in_reply_to_user_id_str":null},"statuses_count":11,"profile_background_color":"C0DEED","profile_background_image_url_https":"https:\/\/si0.twimg.com\/images\/themes\/theme1\/bg.png","profile_background_image_url":"http:\/\/a0.twimg.com\/images\/themes\/theme1\/bg.png","created_at":"Fri Mar 06 19:42:04 +0000 2009","profile_image_url_https":"https:\/\/si0.twimg.com\/profile_images\/1133727344\/floris2_normal.jpg","default_profile_image":false,"lang":"en","profile_text_color":"333333","contributors_enabled":false,"profile_sidebar_fill_color":"DDEEF6","id_str":"23108025","is_translator":false,"default_profile":true,"verified":false,"profile_background_tile":false,"followers_count":170,"protected":false,"follow_request_sent":false,"friends_count":17,"name":"Floris van Alkemade","profile_link_color":"0084B4","profile_image_url":"http:\/\/a0.twimg.com\/profile_images\/1133727344\/floris2_normal.jpg","id":23108025,"show_all_inline_media":false,"following":false,"geo_enabled":false,"notifications":false,"utc_offset":3600,"profile_sidebar_border_color":"C0DEED","location":"The Netherlands"},{"friends_count":483,"profile_background_color":"9ae4e8","protected":false,"profile_image_url_https":"https:\/\/si0.twimg.com\/profile_images\/57027993\/21A_0051_normal.jpg","is_translator":false,"profile_background_image_url":"http:\/\/a1.twimg.com\/profile_background_images\/2884781\/35A_0059.jpg","name":"jonathan wisler","default_profile":false,"follow_request_sent":false,"utc_offset":3600,"profile_text_color":"000000","profile_image_url":"http:\/\/a0.twimg.com\/profile_images\/57027993\/21A_0051_normal.jpg","contributors_enabled":false,"following":false,"profile_sidebar_fill_color":"e0ff92","description":"","location":"Amsterdam","id_str":"14322331","verified":false,"profile_background_tile":false,"followers_count":199,"screen_name":"jpwisler","status":{"place":null,"geo":null,"in_reply_to_user_id":null,"text":"Got Wind? Looks like some good wind for Wednesday evening. Achter werk zeilen? Amsterdam Laser Beams http:\/\/meetu.ps\/1VjJc","retweet_count":0,"id_str":"87830650589167616","favorited":false,"in_reply_to_status_id_str":null,"coordinates":null,"truncated":false,"in_reply_to_screen_name":null,"id":87830650589167616,"in_reply_to_user_id_str":null,"source":"\u003Ca href=\"http:\/\/www.meetup.com\/\" rel=\"nofollow\"\u003EMeetup\u003C\/a\u003E","created_at":"Mon Jul 04 10:30:33 +0000 2011","contributors":null,"retweeted":false,"in_reply_to_status_id":null},"listed_count":3,"url":"http:\/\/magnifyconsulting.com\/","show_all_inline_media":false,"geo_enabled":false,"profile_link_color":"0000ff","id":14322331,"notifications":false,"profile_background_image_url_https":"https:\/\/si0.twimg.com\/profile_background_images\/2884781\/35A_0059.jpg","created_at":"Mon Apr 07 12:35:12 +0000 2008","profile_sidebar_border_color":"87bc44","time_zone":"Amsterdam","default_profile_image":false,"lang":"en","statuses_count":414,"profile_use_background_image":true,"favourites_count":2},{"profile_background_color":"898989","protected":false,"profile_background_image_url":"http:\/\/a1.twimg.com\/profile_background_images\/9230950\/FreeTwitterDesigner.jpg","name":"KeesjanDeelstra","show_all_inline_media":false,"listed_count":52,"geo_enabled":true,"profile_background_image_url_https":"https:\/\/si0.twimg.com\/profile_background_images\/9230950\/FreeTwitterDesigner.jpg","utc_offset":3600,"profile_text_color":"3d3e38","profile_image_url":"http:\/\/a2.twimg.com\/profile_images\/107101390\/foto-keesjan-congres-2008_normal.jpg","following":false,"profile_sidebar_fill_color":"dddddd","profile_image_url_https":"https:\/\/si0.twimg.com\/profile_images\/107101390\/foto-keesjan-congres-2008_normal.jpg","description":"SEO consultant, author Dutch SEO & search Book, SEO tools, seo software http:\/\/www.seoeffect.com, internet marketing, linkbuilding, social media","location":"Haarlem, the Netherlands","id_str":"14612850","verified":false,"profile_background_tile":false,"followers_count":1237,"screen_name":"KeesjanDeelstra","status":{"place":null,"geo":null,"in_reply_to_user_id":null,"text":"is reading Revenge of the crunchy Nerds  @nalden - http:\/\/t.co\/dimRZRX","retweet_count":0,"id_str":"82923737657262080","favorited":false,"in_reply_to_status_id_str":null,"coordinates":null,"truncated":false,"in_reply_to_screen_name":null,"id":82923737657262080,"in_reply_to_user_id_str":null,"source":"\u003Ca href=\"http:\/\/twitter.com\/tweetbutton\" rel=\"nofollow\"\u003ETweet Button\u003C\/a\u003E","created_at":"Mon Jun 20 21:32:14 +0000 2011","contributors":null,"retweeted":false,"in_reply_to_status_id":null},"contributors_enabled":false,"statuses_count":446,"url":"http:\/\/www.interneteffect.com","default_profile_image":false,"profile_link_color":"839241","id":14612850,"notifications":false,"created_at":"Thu May 01 10:55:05 +0000 2008","friends_count":1041,"profile_sidebar_border_color":"414141","is_translator":false,"time_zone":"Amsterdam","default_profile":false,"follow_request_sent":false,"lang":"en","profile_use_background_image":false,"favourites_count":3},{"follow_request_sent":null,"profile_background_color":"0f1015","protected":false,"profile_background_image_url":"http:\/\/a2.twimg.com\/profile_background_images\/285581829\/temp_kuvva_production_64_4127_1.jpeg","name":"Oliver","default_profile":false,"show_all_inline_media":true,"geo_enabled":true,"utc_offset":3600,"profile_text_color":"7e0025","profile_image_url":"http:\/\/a2.twimg.com\/profile_images\/1359580312\/Twitter_profile_picture_Oliver_05-2011_normal.jpg","listed_count":12,"contributors_enabled":false,"following":null,"profile_background_image_url_https":"https:\/\/si0.twimg.com\/profile_background_images\/285581829\/temp_kuvva_production_64_4127_1.jpeg","profile_sidebar_fill_color":"0f1015","description":"Social. Both offline and online. \u2665 Social media. With @tedxams and @nameshapers.","location":"Amsterdam","id_str":"175148470","verified":false,"profile_background_tile":false,"followers_count":280,"profile_image_url_https":"https:\/\/si0.twimg.com\/profile_images\/1359580312\/Twitter_profile_picture_Oliver_05-2011_normal.jpg","screen_name":"odeleeuw","status":{"place":null,"geo":null,"in_reply_to_user_id":null,"text":"YesWeCanteen wint (gedeeld) de #aceVU summerschool. Vet! #rabobank cc @nameshapers cc @vuconnected","retweet_count":0,"id_str":"89334470552981504","favorited":false,"in_reply_to_status_id_str":null,"coordinates":null,"truncated":false,"in_reply_to_screen_name":null,"id":89334470552981504,"in_reply_to_user_id_str":null,"source":"\u003Ca href=\"http:\/\/mobile.twitter.com\" rel=\"nofollow\"\u003EMobile Web\u003C\/a\u003E","created_at":"Fri Jul 08 14:06:12 +0000 2011","contributors":null,"retweeted":false,"in_reply_to_status_id":null},"statuses_count":3358,"url":"http:\/\/www.oliverdeleeuw.nl","profile_link_color":"009da2","id":175148470,"is_translator":false,"default_profile_image":false,"notifications":null,"created_at":"Thu Aug 05 19:24:29 +0000 2010","profile_sidebar_border_color":"0f1015","time_zone":"Amsterdam","friends_count":256,"lang":"en","profile_use_background_image":true,"favourites_count":17},{"is_translator":false,"profile_background_image_url_https":"https:\/\/si0.twimg.com\/images\/themes\/theme1\/bg.png","profile_background_color":"C0DEED","protected":false,"follow_request_sent":null,"profile_background_image_url":"http:\/\/a0.twimg.com\/images\/themes\/theme1\/bg.png","friends_count":76,"name":"Robbert Schuller","statuses_count":386,"default_profile":true,"utc_offset":3600,"profile_text_color":"333333","profile_image_url":"http:\/\/a3.twimg.com\/profile_images\/1414492693\/Image0045_normal.jpg","following":null,"profile_sidebar_fill_color":"DDEEF6","description":"","location":"","id_str":"115476648","listed_count":1,"verified":false,"profile_background_tile":false,"followers_count":36,"screen_name":"RobbertSchuller","status":{"place":null,"geo":null,"in_reply_to_user_id":264407500,"text":"@korttweet Hier is wat te lezen in afwachting van de invite: tcrn.ch\/mQo8Wq   #googleplus","retweet_count":0,"id_str":"89361722623787008","favorited":false,"in_reply_to_status_id_str":null,"coordinates":null,"truncated":false,"in_reply_to_screen_name":"korttweet","id":89361722623787008,"in_reply_to_user_id_str":"264407500","source":"web","created_at":"Fri Jul 08 15:54:29 +0000 2011","contributors":null,"retweeted":false,"in_reply_to_status_id":null},"geo_enabled":false,"url":null,"profile_link_color":"0084B4","profile_image_url_https":"https:\/\/si0.twimg.com\/profile_images\/1414492693\/Image0045_normal.jpg","id":115476648,"show_all_inline_media":false,"notifications":null,"created_at":"Thu Feb 18 19:44:05 +0000 2010","profile_sidebar_border_color":"C0DEED","default_profile_image":false,"contributors_enabled":false,"time_zone":"Amsterdam","lang":"en","profile_use_background_image":true,"favourites_count":0},{"is_translator":false,"profile_background_color":"C0DEED","protected":false,"follow_request_sent":null,"profile_background_image_url":"http:\/\/a3.twimg.com\/profile_background_images\/211011515\/background.jpg","name":"Thom Hoekstra","default_profile":false,"utc_offset":3600,"profile_text_color":"333333","profile_image_url":"http:\/\/a2.twimg.com\/profile_images\/1162639971\/Avatar_1_normal.png","following":null,"profile_sidebar_fill_color":"DDEEF6","description":"Student Communication & Multimedia Design","location":"Harlingen, The Netherlands","id_str":"58770911","listed_count":3,"verified":false,"profile_background_tile":false,"profile_background_image_url_https":"https:\/\/si0.twimg.com\/profile_background_images\/211011515\/background.jpg","followers_count":16,"screen_name":"thomhoekstra","status":{"place":null,"geo":null,"in_reply_to_user_id":6824582,"text":"@eriq en is 't wat?","retweet_count":0,"id_str":"86409715944390657","favorited":false,"in_reply_to_status_id_str":null,"coordinates":null,"truncated":false,"in_reply_to_screen_name":"eriq","id":86409715944390657,"in_reply_to_user_id_str":"6824582","source":"web","created_at":"Thu Jun 30 12:24:16 +0000 2011","contributors":null,"retweeted":false,"in_reply_to_status_id":null},"url":"http:\/\/www.thomhoekstra.nl","profile_image_url_https":"https:\/\/si0.twimg.com\/profile_images\/1162639971\/Avatar_1_normal.png","show_all_inline_media":false,"geo_enabled":true,"profile_link_color":"0084B4","id":58770911,"contributors_enabled":false,"notifications":null,"created_at":"Tue Jul 21 11:29:41 +0000 2009","profile_sidebar_border_color":"C0DEED","default_profile_image":false,"time_zone":"Amsterdam","lang":"en","statuses_count":132,"profile_use_background_image":true,"favourites_count":0,"friends_count":25},{"statuses_count":3377,"profile_background_color":"8B542B","protected":false,"profile_background_image_url":"http:\/\/a2.twimg.com\/profile_background_images\/3900305\/Mister-fish.jpg","name":"Wouter van Doorn","is_translator":false,"default_profile_image":false,"utc_offset":3600,"friends_count":442,"profile_text_color":"333333","profile_image_url":"http:\/\/a0.twimg.com\/profile_images\/1160905780\/woutervandoorn_normal.jpg","default_profile":false,"following":false,"profile_sidebar_fill_color":"EADEAA","description":"crazy about @EllisvdenBosch, daddy, surf 's up, online communication & branding, digital storytelling, AR & QR, digital producer @DPINewMedia","location":"Rotterdam en Scheveningen","id_str":"18970704","follow_request_sent":false,"verified":false,"profile_background_tile":false,"followers_count":322,"screen_name":"woutervandoorn","status":{"place":null,"geo":null,"in_reply_to_user_id":null,"text":"Stand van zaken in Costa Rica. Iedere dag surf, zon, regen en huis gaat snel. Wel druk in de line up met surfen. Al die schildpadden :-) #fb","retweet_count":0,"id_str":"86851823050293248","favorited":false,"in_reply_to_status_id_str":null,"coordinates":null,"truncated":false,"in_reply_to_screen_name":null,"id":86851823050293248,"in_reply_to_user_id_str":null,"source":"\u003Ca href=\"http:\/\/twitter.com\/#!\/download\/ipad\" rel=\"nofollow\"\u003ETwitter for iPad\u003C\/a\u003E","created_at":"Fri Jul 01 17:41:02 +0000 2011","contributors":null,"retweeted":false,"in_reply_to_status_id":null},"url":"http:\/\/www.dpi.nl","profile_link_color":"9D582E","id":18970704,"show_all_inline_media":false,"geo_enabled":true,"notifications":false,"created_at":"Wed Jan 14 08:17:35 +0000 2009","profile_sidebar_border_color":"D9B17E","listed_count":17,"contributors_enabled":false,"profile_background_image_url_https":"https:\/\/si0.twimg.com\/profile_background_images\/3900305\/Mister-fish.jpg","time_zone":"Amsterdam","lang":"en","profile_use_background_image":true,"favourites_count":22,"profile_image_url_https":"https:\/\/si0.twimg.com\/profile_images\/1160905780\/woutervandoorn_normal.jpg"},{"is_translator":false,"profile_background_image_url_https":"https:\/\/si0.twimg.com\/images\/themes\/theme1\/bg.png","profile_background_color":"C0DEED","protected":false,"follow_request_sent":null,"profile_background_image_url":"http:\/\/a0.twimg.com\/images\/themes\/theme1\/bg.png","friends_count":106,"name":"Bouke van Veen","statuses_count":142,"default_profile":true,"utc_offset":null,"profile_text_color":"333333","profile_image_url":"http:\/\/a3.twimg.com\/profile_images\/108359037\/omgwtf_normal.jpg","following":null,"profile_sidebar_fill_color":"DDEEF6","description":"","location":"Amsterdam","id_str":"25991940","listed_count":11,"verified":false,"profile_background_tile":false,"followers_count":73,"screen_name":"kabouke","status":{"place":null,"geo":null,"in_reply_to_user_id":88781203,"text":"@spllr where can we find the latest vids of appsterdam?","retweet_count":0,"id_str":"84394288263331840","favorited":false,"in_reply_to_status_id_str":"84291228442697730","coordinates":null,"truncated":false,"in_reply_to_screen_name":"spllr","id":84394288263331840,"in_reply_to_user_id_str":"88781203","source":"\u003Ca href=\"http:\/\/www.tweetdeck.com\" rel=\"nofollow\"\u003ETweetDeck\u003C\/a\u003E","created_at":"Fri Jun 24 22:55:40 +0000 2011","contributors":null,"retweeted":false,"in_reply_to_status_id":84291228442697730},"geo_enabled":true,"url":"http:\/\/www.freshlyjuiced.nl","profile_link_color":"0084B4","profile_image_url_https":"https:\/\/si0.twimg.com\/profile_images\/108359037\/omgwtf_normal.jpg","id":25991940,"show_all_inline_media":false,"notifications":null,"created_at":"Mon Mar 23 12:33:09 +0000 2009","profile_sidebar_border_color":"C0DEED","default_profile_image":false,"contributors_enabled":false,"time_zone":null,"lang":"en","profile_use_background_image":true,"favourites_count":1},{"profile_background_image_url_https":"https:\/\/si0.twimg.com\/images\/themes\/theme1\/bg.png","profile_background_color":"C0DEED","protected":false,"profile_background_image_url":"http:\/\/a0.twimg.com\/images\/themes\/theme1\/bg.png","profile_image_url_https":"https:\/\/si0.twimg.com\/profile_images\/1122564495\/IMG_0098_normal.jpg","name":"PvF","default_profile_image":false,"contributors_enabled":false,"utc_offset":3600,"profile_text_color":"333333","profile_image_url":"http:\/\/a0.twimg.com\/profile_images\/1122564495\/IMG_0098_normal.jpg","is_translator":false,"following":null,"profile_sidebar_fill_color":"DDEEF6","description":"MDD aka Peter von Frosta aka Stephan Diederich","location":"iPhone: 49.468639,8.483658","id_str":"14711059","default_profile":true,"follow_request_sent":null,"verified":false,"profile_background_tile":false,"friends_count":133,"followers_count":92,"screen_name":"PvF","status":{"place":null,"geo":null,"in_reply_to_user_id":40692769,"text":"@westfeld sicher doch. Du auch?","retweet_count":0,"id_str":"88388260337954816","favorited":false,"in_reply_to_status_id_str":"88287207546306560","coordinates":null,"truncated":false,"in_reply_to_screen_name":"westfeld","id":88388260337954816,"in_reply_to_user_id_str":"40692769","source":"\u003Ca href=\"http:\/\/twitter.com\/#!\/download\/iphone\" rel=\"nofollow\"\u003ETwitter for iPhone\u003C\/a\u003E","created_at":"Tue Jul 05 23:26:18 +0000 2011","contributors":null,"retweeted":false,"in_reply_to_status_id":88287207546306560},"url":null,"show_all_inline_media":false,"geo_enabled":false,"profile_link_color":"0084B4","id":14711059,"notifications":null,"created_at":"Fri May 09 08:02:45 +0000 2008","profile_sidebar_border_color":"C0DEED","listed_count":10,"time_zone":"Berlin","lang":"en","statuses_count":124,"profile_use_background_image":true,"favourites_count":0},{"is_translator":false,"profile_background_color":"C0DEED","protected":true,"default_profile":false,"follow_request_sent":false,"profile_background_image_url":"http:\/\/a1.twimg.com\/profile_background_images\/195509886\/matzwart.jpg","name":"M. Calm\u00e3o Baptista","utc_offset":3600,"profile_text_color":"333333","profile_image_url":"http:\/\/a3.twimg.com\/profile_images\/1231577951\/41403_1052726484_1877_q_normal.jpg","following":false,"profile_sidebar_fill_color":"DDEEF6","description":"Student Nieuwe Media @UvA_Amsterdam | Social Media addict | Webdesigner | Conceptor | Online Marketeer |","location":"Amsterdam","id_str":"241096197","listed_count":1,"verified":false,"profile_background_tile":true,"profile_background_image_url_https":"https:\/\/si0.twimg.com\/profile_background_images\/195509886\/matzwart.jpg","followers_count":41,"screen_name":"MCalmao","url":null,"profile_image_url_https":"https:\/\/si0.twimg.com\/profile_images\/1231577951\/41403_1052726484_1877_q_normal.jpg","show_all_inline_media":false,"geo_enabled":true,"profile_link_color":"0084B4","id":241096197,"contributors_enabled":false,"notifications":false,"created_at":"Fri Jan 21 13:06:52 +0000 2011","profile_sidebar_border_color":"C0DEED","default_profile_image":false,"time_zone":"Amsterdam","lang":"en","statuses_count":28,"profile_use_background_image":true,"favourites_count":0,"friends_count":232},{"profile_background_image_url_https":"https:\/\/si0.twimg.com\/profile_background_images\/173204806\/Wolf.jpg","profile_background_color":"001329","protected":false,"profile_background_image_url":"http:\/\/a3.twimg.com\/profile_background_images\/173204806\/Wolf.jpg","profile_image_url_https":"https:\/\/si0.twimg.com\/profile_images\/1311085841\/IMG_0628_normal.jpg","name":"Thijs Gitmans","default_profile_image":false,"contributors_enabled":false,"utc_offset":3600,"profile_text_color":"1f0b9e","profile_image_url":"http:\/\/a3.twimg.com\/profile_images\/1311085841\/IMG_0628_normal.jpg","is_translator":false,"following":false,"profile_sidebar_fill_color":"ffffff","description":"Peak Capital, Brand New Day, Ajax, Nijmegen-Groningen-Amsterdam, Piet Boot, Apple, Muziek, Spotify, Cowboy Henk, Eten-drinken-eten, New ventures","location":"Amsterdam","id_str":"126781702","follow_request_sent":false,"verified":false,"profile_background_tile":true,"friends_count":544,"followers_count":357,"screen_name":"tgitmans","status":{"place":null,"geo":null,"in_reply_to_user_id":25139926,"text":"@erwindrenth en weer n avond eten overslaan lijkt me slecht plan #eatingischeating","retweet_count":0,"id_str":"89365404870385664","favorited":false,"in_reply_to_status_id_str":"89363436244447232","coordinates":null,"truncated":false,"in_reply_to_screen_name":"erwindrenth","id":89365404870385664,"in_reply_to_user_id_str":"25139926","source":"\u003Ca href=\"http:\/\/www.osfoora.com\" rel=\"nofollow\"\u003EOsfoora for iPhone\u003C\/a\u003E","created_at":"Fri Jul 08 16:09:07 +0000 2011","contributors":null,"retweeted":false,"in_reply_to_status_id":89363436244447232},"url":"http:\/\/brandnewdayvermogensbeheer.nl","default_profile":false,"show_all_inline_media":false,"geo_enabled":true,"profile_link_color":"075de8","id":126781702,"notifications":false,"created_at":"Sat Mar 27 00:13:12 +0000 2010","profile_sidebar_border_color":"e6da2b","listed_count":17,"time_zone":"Amsterdam","lang":"en","statuses_count":6229,"profile_use_background_image":true,"favourites_count":8},{"listed_count":32,"time_zone":"Amsterdam","screen_name":"Almar","statuses_count":4075,"profile_use_background_image":true,"favourites_count":391,"url":"http:\/\/www.virvie.com","description":"Being a virreal architect means that I aim to realize the online equivalent of skyscrapers","status":{"contributors":null,"retweeted":false,"in_reply_to_status_id":89275548064428033,"text":"@newrafael Unbelievable!","created_at":"Fri Jul 08 11:20:14 +0000 2011","source":"\u003Ca href=\"http:\/\/itunes.apple.com\/us\/app\/twitter\/id409789998?mt=12\" rel=\"nofollow\"\u003ETwitter for Mac\u003C\/a\u003E","geo":null,"in_reply_to_user_id":205848948,"place":null,"retweet_count":0,"id_str":"89292703346589696","favorited":false,"in_reply_to_status_id_str":"89275548064428033","coordinates":null,"truncated":false,"in_reply_to_screen_name":"newrafael","id":89292703346589696,"in_reply_to_user_id_str":"205848948"},"profile_background_image_url_https":"https:\/\/si0.twimg.com\/profile_background_images\/127223998\/Hong_Kong_Skyline_with_logo_small__for_Twitter_.jpg","profile_background_color":"dedbdb","profile_background_image_url":"http:\/\/a0.twimg.com\/profile_background_images\/127223998\/Hong_Kong_Skyline_with_logo_small__for_Twitter_.jpg","created_at":"Mon Jun 04 17:59:20 +0000 2007","profile_image_url_https":"https:\/\/si0.twimg.com\/profile_images\/27512652\/almar_contour_logor_normal.jpg","default_profile_image":false,"contributors_enabled":false,"lang":"en","profile_text_color":"333333","is_translator":false,"profile_sidebar_fill_color":"e6fa84","id_str":"6575982","follow_request_sent":false,"verified":false,"profile_background_tile":false,"friends_count":685,"followers_count":550,"protected":false,"name":"Almar van der Krogt","default_profile":false,"show_all_inline_media":false,"geo_enabled":true,"profile_link_color":"0084B4","profile_image_url":"http:\/\/a3.twimg.com\/profile_images\/27512652\/almar_contour_logor_normal.jpg","id":6575982,"following":false,"notifications":false,"utc_offset":3600,"profile_sidebar_border_color":"00ff55","location":"Deventer, the Netherlands"},{"is_translator":false,"profile_background_image_url_https":"https:\/\/si0.twimg.com\/images\/themes\/theme15\/bg.png","profile_background_color":"262626","protected":false,"follow_request_sent":null,"profile_background_image_url":"http:\/\/a0.twimg.com\/images\/themes\/theme15\/bg.png","friends_count":54,"name":"carlosmouter","statuses_count":2387,"default_profile":false,"utc_offset":-10800,"profile_text_color":"333333","profile_image_url":"http:\/\/a2.twimg.com\/profile_images\/1359513527\/twitter_normal.jpg","following":null,"profile_sidebar_fill_color":"e6e6e6","description":"CS Student, web, python, django, objective-c. Ik doe ook analoge dingen zoals slapen, eten en tuinieren.","location":"Almere","id_str":"60852037","listed_count":7,"verified":false,"profile_background_tile":false,"followers_count":45,"screen_name":"carlosmouter","status":{"place":null,"geo":null,"in_reply_to_user_id":50375999,"text":"@pfiene verder studeren? #indetoekomst","retweet_count":0,"id_str":"89338760403234816","favorited":false,"in_reply_to_status_id_str":"89333085732216832","coordinates":null,"truncated":false,"in_reply_to_screen_name":"pfiene","id":89338760403234816,"in_reply_to_user_id_str":"50375999","source":"web","created_at":"Fri Jul 08 14:23:14 +0000 2011","contributors":null,"retweeted":false,"in_reply_to_status_id":89333085732216832},"geo_enabled":false,"url":null,"profile_link_color":"185f85","profile_image_url_https":"https:\/\/si0.twimg.com\/profile_images\/1359513527\/twitter_normal.jpg","id":60852037,"show_all_inline_media":true,"notifications":null,"created_at":"Tue Jul 28 08:38:06 +0000 2009","profile_sidebar_border_color":"d6d6d6","default_profile_image":false,"contributors_enabled":false,"time_zone":"Greenland","lang":"en","profile_use_background_image":false,"favourites_count":4},{"is_translator":false,"profile_background_color":"C0DEED","protected":false,"follow_request_sent":false,"profile_background_image_url":"http:\/\/a1.twimg.com\/profile_background_images\/265106756\/techmapsq.png","name":"techMAP Amsterdam","utc_offset":null,"profile_text_color":"333333","profile_image_url":"http:\/\/a1.twimg.com\/profile_images\/1384128261\/techmapsq_normal.png","following":false,"profile_sidebar_fill_color":"DDEEF6","description":"technology. Marketing. Advertising. Pr. #techMAP. Join the community and learn at monthly events: www.meetup.com\/techmapamsterdam","location":"Amsterdam","id_str":"311973743","listed_count":4,"verified":false,"profile_background_tile":true,"profile_background_image_url_https":"https:\/\/si0.twimg.com\/profile_background_images\/265106756\/techmapsq.png","followers_count":79,"screen_name":"techMAPams","status":{"retweeted_status":{"place":null,"geo":null,"in_reply_to_user_id":null,"text":"Looking for a visual designer for new project for #Layar, are you available right away for 2 months please contact me! Plz RT.","retweet_count":3,"id_str":"89338234840158210","favorited":false,"in_reply_to_status_id_str":null,"coordinates":null,"truncated":false,"in_reply_to_screen_name":null,"id":89338234840158210,"in_reply_to_user_id_str":null,"source":"\u003Ca href=\"http:\/\/www.hootsuite.com\" rel=\"nofollow\"\u003EHootSuite\u003C\/a\u003E","created_at":"Fri Jul 08 14:21:09 +0000 2011","contributors":null,"retweeted":false,"in_reply_to_status_id":null},"place":null,"geo":null,"in_reply_to_user_id":null,"text":"RT @bernicemw: Looking for a visual designer for new project for #Layar, are you available right away for 2 months please contact me! Pl ...","retweet_count":3,"id_str":"89339928080695296","favorited":false,"in_reply_to_status_id_str":null,"coordinates":null,"truncated":true,"in_reply_to_screen_name":null,"id":89339928080695296,"in_reply_to_user_id_str":null,"source":"\u003Ca href=\"http:\/\/www.tweetdeck.com\" rel=\"nofollow\"\u003ETweetDeck\u003C\/a\u003E","created_at":"Fri Jul 08 14:27:53 +0000 2011","contributors":null,"retweeted":false,"in_reply_to_status_id":null},"url":"http:\/\/www.wearetechmap.com","profile_image_url_https":"https:\/\/si0.twimg.com\/profile_images\/1384128261\/techmapsq_normal.png","default_profile":false,"show_all_inline_media":false,"geo_enabled":false,"profile_link_color":"0084B4","id":311973743,"contributors_enabled":false,"notifications":false,"created_at":"Mon Jun 06 11:29:43 +0000 2011","profile_sidebar_border_color":"C0DEED","default_profile_image":false,"time_zone":null,"lang":"en","statuses_count":130,"profile_use_background_image":true,"favourites_count":0,"friends_count":254},{"is_translator":false,"profile_background_color":"1A1B1F","protected":false,"follow_request_sent":false,"profile_background_image_url":"http:\/\/a2.twimg.com\/profile_background_images\/34825427\/Twitter.jpg","name":"Martijn Th\u00e9","utc_offset":3600,"profile_text_color":"666666","profile_image_url":"http:\/\/a2.twimg.com\/profile_images\/401110358\/Lucky_cat_normal.jpg","default_profile":false,"following":false,"profile_sidebar_fill_color":"252429","description":"Owner of Noodlewerk.com, Dutch iPhone & iPad app design and development company, e.g. for VPRO's Luisterpaal. Founder of fashion start-up Hollund.","location":"iPhone: 52.080288,4.296817","id_str":"43738948","listed_count":22,"verified":false,"profile_background_tile":false,"profile_background_image_url_https":"https:\/\/si0.twimg.com\/profile_background_images\/34825427\/Twitter.jpg","followers_count":259,"screen_name":"martijnthe","status":{"place":{"place_type":"city","bounding_box":{"coordinates":[[[4.5506397,52.2144983],[4.8190828,52.2144983],[4.8190828,52.3862622],[4.5506397,52.3862622]]],"type":"Polygon"},"name":"Haarlemmermeer","url":"http:\/\/api.twitter.com\/1\/geo\/id\/cd003ebe3a96fcc6.json","id":"cd003ebe3a96fcc6","country":"The Netherlands","country_code":"NL","full_name":"Haarlemmermeer, North Holland","attributes":{}},"geo":{"coordinates":[52.26914525,4.66104972],"type":"Point"},"in_reply_to_user_id":176626960,"text":"@matthieusavary thnx I'll look into it after my (offline) vacation!","retweet_count":0,"id_str":"88048694989045760","favorited":false,"in_reply_to_status_id_str":"87998000110125056","coordinates":{"coordinates":[4.66104972,52.26914525],"type":"Point"},"truncated":false,"in_reply_to_screen_name":"matthieusavary","id":88048694989045760,"in_reply_to_user_id_str":"176626960","source":"\u003Ca href=\"http:\/\/twitter.com\/#!\/download\/iphone\" rel=\"nofollow\"\u003ETwitter for iPhone\u003C\/a\u003E","created_at":"Tue Jul 05 00:56:59 +0000 2011","contributors":null,"retweeted":false,"in_reply_to_status_id":87998000110125056},"url":"http:\/\/www.martijnthe.nl\/","profile_image_url_https":"https:\/\/si0.twimg.com\/profile_images\/401110358\/Lucky_cat_normal.jpg","show_all_inline_media":false,"geo_enabled":true,"profile_link_color":"2FC2EF","id":43738948,"contributors_enabled":false,"notifications":false,"created_at":"Sun May 31 19:24:25 +0000 2009","profile_sidebar_border_color":"181A1E","default_profile_image":false,"time_zone":"Amsterdam","lang":"en","statuses_count":554,"profile_use_background_image":true,"favourites_count":2,"friends_count":224}], "next_cursor":1372767952903519854, "previous_cursor":-1372769062168164082, "next_cursor_str":"1372767952903519854", "previous_cursor_str":"-1372769062168164082"}